unit_converter/parser.py
unit_converter/converter.py
unit_converter/data.py
unit_converter/__init__.py
unit_converter/exceptions.py
unit_converter/units.py
unit_converter-1.0.0.dist-info/metadata.json
unit_converter-1.0.0.dist-info/WHEEL
unit_converter-1.0.0.dist-info/RECORD
unit_converter-1.0.0.dist-info/METADATA
unit_converter-1.0.0.dist-info/DESCRIPTION.rst
unit_converter-1.0.0.dist-info/top_level.txt
