Metadata-Version: 2.0
Name: unit-converter
Version: 1.0.0
Summary: Package for converting quantities in different unit.
Home-page: https://bitbucket.org/jocelynlopez/unit_converter
Author: Jocelyn LOPEZ
Author-email: jocelyn.lopez.pro@gmail.com
License: MIT
Keywords: converter units sciences
Platform: UNKNOWN
Classifier: Development Status :: 1 - Planning
Classifier: Intended Audience :: Developers
Classifier: Intended Audience :: Science/Research
Classifier: Intended Audience :: End Users/Desktop
Classifier: Natural Language :: English
Classifier: License :: OSI Approved :: MIT License
Classifier: Programming Language :: Python
Classifier: Programming Language :: Python :: 3.6
